trendingbot/__init__.py
trendingbot/schedule.py
trendingbot/scrape.py
trendingbot-0.0.3.dist-info/METADATA
trendingbot-0.0.3.dist-info/WHEEL
trendingbot-0.0.3.dist-info/top_level.txt
trendingbot-0.0.3.dist-info/RECORD
