Metadata-Version: 2.1
Name: trendingbot
Version: 0.0.3
Summary: trendingbot
Home-page: https://github.com/yasuo626/TrendingBot
Author: aidroid
Author-email: yasuo626.com@gmail.com
Keywords: trendingbot
Classifier: Programming Language :: Python :: 3
Classifier: License :: OSI Approved :: MIT License
Classifier: Operating System :: OS Independent
Requires-Python: >=3.6
Requires-Dist: requests (==2.30.0)
Requires-Dist: beautifulsoup4 (==2.4.1)
